stock_utils_chho33/__init__.py
stock_utils_chho33/backtest/__init__.py
stock_utils_chho33/backtest/constants.py
stock_utils_chho33/backtest/models.py
stock_utils_chho33/backtest/utils.py
stock_utils_chho33-0.0.43.dist-info/LICENSE
stock_utils_chho33-0.0.43.dist-info/METADATA
stock_utils_chho33-0.0.43.dist-info/WHEEL
stock_utils_chho33-0.0.43.dist-info/top_level.txt
stock_utils_chho33-0.0.43.dist-info/RECORD
